dynatrace/_vendor/google/protobuf/__init__.py
dynatrace/_vendor/google/protobuf/_version.py
dynatrace/_vendor/google/protobuf/any_pb2.py
dynatrace/_vendor/google/protobuf/api_pb2.py
dynatrace/_vendor/google/protobuf/descriptor.py
dynatrace/_vendor/google/protobuf/descriptor_database.py
dynatrace/_vendor/google/protobuf/descriptor_pb2.py
dynatrace/_vendor/google/protobuf/descriptor_pool.py
dynatrace/_vendor/google/protobuf/duration_pb2.py
dynatrace/_vendor/google/protobuf/empty_pb2.py
dynatrace/_vendor/google/protobuf/field_mask_pb2.py
dynatrace/_vendor/google/protobuf/json_format.py
dynatrace/_vendor/google/protobuf/message.py
dynatrace/_vendor/google/protobuf/message_factory.py
dynatrace/_vendor/google/protobuf/proto_builder.py
dynatrace/_vendor/google/protobuf/reflection.py
dynatrace/_vendor/google/protobuf/service.py
dynatrace/_vendor/google/protobuf/service_reflection.py
dynatrace/_vendor/google/protobuf/source_context_pb2.py
dynatrace/_vendor/google/protobuf/struct_pb2.py
dynatrace/_vendor/google/protobuf/symbol_database.py
dynatrace/_vendor/google/protobuf/text_encoding.py
dynatrace/_vendor/google/protobuf/text_format.py
dynatrace/_vendor/google/protobuf/timestamp_pb2.py
dynatrace/_vendor/google/protobuf/type_pb2.py
dynatrace/_vendor/google/protobuf/unknown_fields.py
dynatrace/_vendor/google/protobuf/wrappers_pb2.py
dynatrace/_vendor/google/protobuf/compiler/__init__.py
dynatrace/_vendor/google/protobuf/compiler/plugin_pb2.py
dynatrace/_vendor/google/protobuf/internal/__init__.py
dynatrace/_vendor/google/protobuf/internal/_parameterized.py
dynatrace/_vendor/google/protobuf/internal/api_implementation.py
dynatrace/_vendor/google/protobuf/internal/builder.py
dynatrace/_vendor/google/protobuf/internal/containers.py
dynatrace/_vendor/google/protobuf/internal/decoder.py
dynatrace/_vendor/google/protobuf/internal/encoder.py
dynatrace/_vendor/google/protobuf/internal/enum_type_wrapper.py
dynatrace/_vendor/google/protobuf/internal/extension_dict.py
dynatrace_opentelemetry_core-1.329.2.dist-info/METADATA
dynatrace_opentelemetry_core-1.329.2.dist-info/WHEEL
dynatrace_opentelemetry_core-1.329.2.dist-info/licenses/LICENSE
dynatrace_opentelemetry_core-1.329.2.dist-info/RECORD
